_spake2_cffi.abi3.so
spake2_cffi-1.0.0.dist-info/top_level.txt
spake2_cffi-1.0.0.dist-info/LICENSE
spake2_cffi-1.0.0.dist-info/RECORD
spake2_cffi-1.0.0.dist-info/WHEEL
spake2_cffi-1.0.0.dist-info/METADATA
spake2/build_spake2.py
spake2/spake2.py
spake2/test.py
spake2/__init__.py
